umbrella/__init__.py
raincoat_umbrella-2.0.0.dist-info/LICENSE
raincoat_umbrella-2.0.0.dist-info/METADATA
raincoat_umbrella-2.0.0.dist-info/WHEEL
raincoat_umbrella-2.0.0.dist-info/entry_points.txt
raincoat_umbrella-2.0.0.dist-info/top_level.txt
raincoat_umbrella-2.0.0.dist-info/zip-safe
raincoat_umbrella-2.0.0.dist-info/RECORD
