Metadata-Version: 2.1
Name: raincoat-umbrella
Version: 2.0.0
Summary: "This package is an exemple package to showcase Raincoat."
Home-page: https://github.com/ewjoachim/umbrella
Author: Joachim Jablon
Author-email: ewjoachim@gmail.com
License: WTFPL
Keywords: code,diff,copy-paste,linter,DRY
Classifier: Development Status :: 5 - Production/Stable
Classifier: Intended Audience :: Developers
Classifier: License :: OSI Approved
Classifier: Programming Language :: Python :: 3
Classifier: Programming Language :: Python :: 3.6
License-File: LICENSE
